galleries_qt/__init__.py
galleries_qt/galleries_combobox.py
galleries_qt/galleries_manager.py
galleries_qt/galleries_manager.ui
galleries_qt/gallery_annotations_parser_view.py
galleries_qt/gallery_wizard.py
galleries_qt/gallery_wizard.ui
galleries_qt/parser_widgets/__init__.py
galleries_qt/parser_widgets/file_name_parser_widget.py
galleries_qt/parser_widgets/file_name_parser_widget.ui
galleries_qt/parser_widgets/settings_parser_widget.py
galleries_qt-0.4.3.dist-info/LICENSE
galleries_qt-0.4.3.dist-info/METADATA
galleries_qt-0.4.3.dist-info/WHEEL
galleries_qt-0.4.3.dist-info/top_level.txt
galleries_qt-0.4.3.dist-info/RECORD
